<?xml version="1.0" encoding="UTF-16"?>
<!--

rem @file
rem
rem PyRobotServer XML for adding a scheduled task to start PyRobotRemote.py.
rem
rem Copyright (c), Microsoft Corporation
rem SPDX-License-Identifier: BSD-2-Clause-Patent

 -->
<Task version="1.4" xmlns="http://schemas.microsoft.com/windows/2004/02/mit/task">
  <RegistrationInfo>
    <Date>2017-01-25T13:15:07.3865747</Date>
    <Author>TestCase Creator</Author>
    <URI>\robotserver</URI>
  </RegistrationInfo>
  <Triggers>
    <LogonTrigger>
      <Enabled>true</Enabled>
    </LogonTrigger>
  </Triggers>
  <Principals>
    <Principal id="Author">
      <LogonType>InteractiveToken</LogonType>
      <RunLevel>HighestAvailable</RunLevel>
    </Principal>
  </Principals>
  <Settings>
    <MultipleInstancesPolicy>IgnoreNew</MultipleInstancesPolicy>
    <DisallowStartIfOnBatteries>false</DisallowStartIfOnBatteries>
    <StopIfGoingOnBatteries>false</StopIfGoingOnBatteries>
    <AllowHardTerminate>true</AllowHardTerminate>
    <StartWhenAvailable>false</StartWhenAvailable>
    <RunOnlyIfNetworkAvailable>false</RunOnlyIfNetworkAvailable>
    <IdleSettings>
      <StopOnIdleEnd>true</StopOnIdleEnd>
      <RestartOnIdle>false</RestartOnIdle>
    </IdleSettings>
    <AllowStartOnDemand>true</AllowStartOnDemand>
    <Enabled>true</Enabled>
    <Hidden>false</Hidden>
    <RunOnlyIfIdle>false</RunOnlyIfIdle>
    <DisallowStartOnRemoteAppSession>false</DisallowStartOnRemoteAppSession>
    <UseUnifiedSchedulingEngine>true</UseUnifiedSchedulingEngine>
    <WakeToRun>false</WakeToRun>
    <ExecutionTimeLimit>PT0S</ExecutionTimeLimit>
    <Priority>7</Priority>
  </Settings>
  <Actions Context="Author">
    <Exec>
      <Command>C:\Python311\python</Command>
      <Arguments>C:\Test\PyRobotRemote.py</Arguments>
      <WorkingDirectory>C:\Test</WorkingDirectory>
    </Exec>
  </Actions>
</Task>